[
    {
        "load": 231.56,
        "cpu_time": 233531
    },
    {
        "id": "https://www.google.com/",
        "objs": [
            {
                "activityId": "Networking_0",
                "id": "8739F37D9620299FE50FEA2B16BAFB1B",
                "startTime": 0.0,
                "endTime": 36.91,
                "mimeType": "text/html",
                "url": "https://www.google.com/",
                "fromScript": "Null",
                "transferSize": 5250,
                "responseReceivedTime": 0.061,
                "statusCode": 200
            },
            {
                "activityId": "Scripting_0",
                "url": "https://www.google.com/",
                "startTime": 19.043,
                "endTime": 28.308
            },
            {
                "activityId": "Scripting_1",
                "url": "https://www.google.com/",
                "startTime": 33.532,
                "endTime": 35.071
            },
            {
                "activityId": "Scripting_2",
                "url": "https://www.google.com/",
                "startTime": 40.24,
                "endTime": 40.33
            },
            {
                "activityId": "Scripting_3",
                "url": "https://www.google.com/",
                "startTime": 41.03,
                "endTime": 41.507
            },
            {
                "activityId": "Scripting_4",
                "url": "https://www.google.com/",
                "startTime": 41.766,
                "endTime": 47.519
            },
            {
                "activityId": "Scripting_5",
                "url": "https://www.google.com/",
                "startTime": 48.315,
                "endTime": 49.245
            },
            {
                "activityId": "Scripting_6",
                "url": "https://www.google.com/",
                "startTime": 49.32,
                "endTime": 68.251
            },
            {
                "activityId": "Loading_0",
                "fromScript": null,
                "styleSheetUrl": null,
                "url": "https://www.google.com/",
                "name": "ParseHTML",
                "startTime": 18.196,
                "endTime": 28.352
            },
            {
                "activityId": "Loading_1",
                "fromScript": null,
                "styleSheetUrl": null,
                "url": "https://www.google.com/",
                "name": "ParseHTML",
                "startTime": 30.024,
                "endTime": 36.129
            },
            {
                "activityId": "Loading_2",
                "fromScript": null,
                "styleSheetUrl": null,
                "url": "https://www.google.com/",
                "name": "ParseHTML",
                "startTime": 40.195,
                "endTime": 40.633
            },
            {
                "activityId": "Loading_3",
                "fromScript": null,
                "styleSheetUrl": null,
                "url": "https://www.google.com/",
                "name": "ParseHTML",
                "startTime": 40.979,
                "endTime": 71.507
            }
        ]
    },
    {
        "id": "https://www.google.com/images/branding/googlelogo/1x/googlelogo_color_272x92dp.png",
        "objs": [
            {
                "activityId": "Networking_1",
                "id": "1000028570.2",
                "startTime": 29.137,
                "endTime": 195.192,
                "mimeType": "image/png",
                "url": "https://www.google.com/images/branding/googlelogo/1x/googlelogo_color_272x92dp.png",
                "fromScript": "Null",
                "transferSize": 5969,
                "responseReceivedTime": 195.01,
                "statusCode": 200
            }
        ]
    },
    {
        "id": "https://ssl.gstatic.com/gb/images/i1_1967ca6a.png",
        "objs": [
            {
                "activityId": "Networking_2",
                "id": "1000028570.5",
                "startTime": 50.38,
                "endTime": 73.778,
                "mimeType": "image/png",
                "url": "https://ssl.gstatic.com/gb/images/i1_1967ca6a.png",
                "fromScript": "https://www.google.com/",
                "transferSize": 7325,
                "responseReceivedTime": 73.525,
                "statusCode": 200
            }
        ]
    },
    {
        "id": "https://www.gstatic.com/images/branding/googlemic/2x/googlemic_color_24dp.png",
        "objs": [
            {
                "activityId": "Networking_3",
                "id": "1000028570.6",
                "startTime": 50.897,
                "endTime": 77.642,
                "mimeType": "image/png",
                "url": "https://www.gstatic.com/images/branding/googlemic/2x/googlemic_color_24dp.png",
                "fromScript": "https://www.google.com/",
                "transferSize": 646,
                "responseReceivedTime": 74.816,
                "statusCode": 200
            }
        ]
    },
    {
        "id": "https://www.google.com/images/nav_logo299.webp",
        "objs": [
            {
                "activityId": "Networking_4",
                "id": "1000028570.7",
                "startTime": 71.104,
                "endTime": 194.799,
                "mimeType": "image/webp",
                "url": "https://www.google.com/images/nav_logo299.webp",
                "fromScript": "Null",
                "transferSize": 4396,
                "responseReceivedTime": 194.585,
                "statusCode": 200
            }
        ]
    },
    {
        "id": "https://www.google.com/xjs/_/js/k=xjs.s.ja.j58xPhmAgxo.O/m=Fkg7bd,HcFEGb,IvlUe,MC8mtf,OF7gzc,RMhBfe,T4BAC,TJw5qb,TbaHGc,Y33vzc,cdos,hsm,iDPoPb,jsa,mvYTse,tg8oTe,uz938c,vWNDde,ws9Tlc,yQ43ff,d,csi/am=AABgEdi7AyH_XwEAdgEABO4CG1kgQWhYNUA/d=1/dg=2/rs=ACT90oFcVY11Ri6VJM2k9nn_0zK4FLum3Q",
        "objs": [
            {
                "activityId": "Networking_5",
                "id": "1000028570.8",
                "startTime": 74.433,
                "endTime": 127.712,
                "mimeType": "text/javascript",
                "url": "https://www.google.com/xjs/_/js/k=xjs.s.ja.j58xPhmAgxo.O/m=Fkg7bd,HcFEGb,IvlUe,MC8mtf,OF7gzc,RMhBfe,T4BAC,TJw5qb,TbaHGc,Y33vzc,cdos,hsm,iDPoPb,jsa,mvYTse,tg8oTe,uz938c,vWNDde,ws9Tlc,yQ43ff,d,csi/am=AABgEdi7AyH_XwEAdgEABO4CG1kgQWhYNUA/d=1/dg=2/rs=ACT90oFcVY11Ri6VJM2k9nn_0zK4FLum3Q",
                "fromScript": "https://www.google.com/",
                "transferSize": 9219,
                "responseReceivedTime": 117.728,
                "statusCode": 200
            },
            {
                "activityId": "Scripting_7",
                "url": "https://www.google.com/xjs/_/js/k=xjs.s.ja.j58xPhmAgxo.O/m=Fkg7bd,HcFEGb,IvlUe,MC8mtf,OF7gzc,RMhBfe,T4BAC,TJw5qb,TbaHGc,Y33vzc,cdos,hsm,iDPoPb,jsa,mvYTse,tg8oTe,uz938c,vWNDde,ws9Tlc,yQ43ff,d,csi/am=AABgEdi7AyH_XwEAdgEABO4CG1kgQWhYNUA/d=1/dg=2/rs=ACT90oFcVY11Ri6VJM2k9nn_0zK4FLum3Q",
                "startTime": 135.222,
                "endTime": 194.286
            }
        ]
    },
    {
        "id": "https://www.google.com/xjs/_/js/k=xjs.s.ja.j58xPhmAgxo.O/am=AABgEdi7AyH_XwEAdgEABO4CG1kgQWhYNUA/d=1/exm=Fkg7bd,HcFEGb,IvlUe,MC8mtf,OF7gzc,RMhBfe,T4BAC,TJw5qb,TbaHGc,Y33vzc,cdos,csi,d,hsm,iDPoPb,jsa,mvYTse,tg8oTe,uz938c,vWNDde,ws9Tlc,yQ43ff/ed=1/dg=2/rs=ACT90oFcVY11Ri6VJM2k9nn_0zK4FLum3Q/m=WgDvvc,aa,abd,async,dvl,fEVMic,foot,lu,m,mUpTid,mu,sb_wiz,sf,sonic,spch,xz7cCd?xjs=s1",
        "objs": [
            {
                "activityId": "Networking_6",
                "id": "1000028570.9",
                "startTime": 207.347,
                "endTime": 213.238,
                "mimeType": "text/javascript",
                "url": "https://www.google.com/xjs/_/js/k=xjs.s.ja.j58xPhmAgxo.O/am=AABgEdi7AyH_XwEAdgEABO4CG1kgQWhYNUA/d=1/exm=Fkg7bd,HcFEGb,IvlUe,MC8mtf,OF7gzc,RMhBfe,T4BAC,TJw5qb,TbaHGc,Y33vzc,cdos,csi,d,hsm,iDPoPb,jsa,mvYTse,tg8oTe,uz938c,vWNDde,ws9Tlc,yQ43ff/ed=1/dg=2/rs=ACT90oFcVY11Ri6VJM2k9nn_0zK4FLum3Q/m=WgDvvc,aa,abd,async,dvl,fEVMic,foot,lu,m,mUpTid,mu,sb_wiz,sf,sonic,spch,xz7cCd?xjs=s1",
                "fromScript": "https://www.google.com/xjs/_/js/k=xjs.s.ja.j58xPhmAgxo.O/m=Fkg7bd,HcFEGb,IvlUe,MC8mtf,OF7gzc,RMhBfe,T4BAC,TJw5qb,TbaHGc,Y33vzc,cdos,hsm,iDPoPb,jsa,mvYTse,tg8oTe,uz938c,vWNDde,ws9Tlc,yQ43ff,d,csi/am=AABgEdi7AyH_XwEAdgEABO4CG1kgQWhYNUA/d=1/dg=2/rs=ACT90oFcVY11Ri6VJM2k9nn_0zK4FLum3Q",
                "transferSize": 34929,
                "responseReceivedTime": 212.674,
                "statusCode": 200
            },
            {
                "activityId": "Scripting_8",
                "url": "https://www.google.com/xjs/_/js/k=xjs.s.ja.j58xPhmAgxo.O/am=AABgEdi7AyH_XwEAdgEABO4CG1kgQWhYNUA/d=1/exm=Fkg7bd,HcFEGb,IvlUe,MC8mtf,OF7gzc,RMhBfe,T4BAC,TJw5qb,TbaHGc,Y33vzc,cdos,csi,d,hsm,iDPoPb,jsa,mvYTse,tg8oTe,uz938c,vWNDde,ws9Tlc,yQ43ff/ed=1/dg=2/rs=ACT90oFcVY11Ri6VJM2k9nn_0zK4FLum3Q/m=WgDvvc,aa,abd,async,dvl,fEVMic,foot,lu,m,mUpTid,mu,sb_wiz,sf,sonic,spch,xz7cCd?xjs=s1",
                "startTime": 218.129,
                "endTime": 227.851
            }
        ]
    },
    {
        "id": "Rendering",
        "objs": [
            {
                "activityId": "Rendering_0",
                "startTime": 34.566,
                "name": "Layout",
                "endTime": 34.729
            },
            {
                "activityId": "Rendering_1",
                "startTime": 51.467,
                "name": "Layout",
                "endTime": 67.798
            },
            {
                "activityId": "Rendering_2",
                "startTime": 71.875,
                "name": "UpdateLayerTree",
                "endTime": 72.206
            },
            {
                "activityId": "Rendering_3",
                "startTime": 75.189,
                "name": "UpdateLayerTree",
                "endTime": 75.243
            },
            {
                "activityId": "Rendering_4",
                "startTime": 82.469,
                "name": "UpdateLayerTree",
                "endTime": 82.50699999999999
            },
            {
                "activityId": "Rendering_5",
                "startTime": 195.483,
                "name": "UpdateLayerTree",
                "endTime": 195.532
            },
            {
                "activityId": "Rendering_6",
                "startTime": 212.09,
                "name": "UpdateLayerTree",
                "endTime": 212.104
            },
            {
                "activityId": "Rendering_7",
                "startTime": 232.612,
                "name": "UpdateLayerTree",
                "endTime": 232.626
            }
        ]
    },
    {
        "id": "Painting",
        "objs": [
            {
                "activityId": "Painting_5",
                "startTime": 15.502,
                "name": "CompositeLayers",
                "endTime": 15.809,
                "layerTreeId": 1
            },
            {
                "activityId": "Painting_6",
                "startTime": 29.119,
                "name": "CompositeLayers",
                "endTime": 29.454,
                "layerTreeId": 1
            },
            {
                "activityId": "Painting_7",
                "startTime": 47.446,
                "name": "CompositeLayers",
                "endTime": 47.519,
                "layerTreeId": 1
            },
            {
                "activityId": "Painting_8",
                "startTime": 62.345,
                "name": "CompositeLayers",
                "endTime": 62.474,
                "layerTreeId": 1
            },
            {
                "activityId": "Painting_9",
                "startTime": 72.224,
                "name": "Paint",
                "endTime": 72.51
            },
            {
                "activityId": "Painting_10",
                "startTime": 72.526,
                "name": "Paint",
                "endTime": 72.56
            },
            {
                "activityId": "Painting_11",
                "startTime": 72.955,
                "name": "CompositeLayers",
                "endTime": 73.068,
                "layerTreeId": 1
            },
            {
                "activityId": "Painting_12",
                "startTime": 75.255,
                "name": "Paint",
                "endTime": 75.314
            },
            {
                "activityId": "Painting_13",
                "startTime": 75.392,
                "name": "CompositeLayers",
                "endTime": 77.421,
                "layerTreeId": 1
            },
            {
                "activityId": "Painting_14",
                "startTime": 79.264,
                "name": "CompositeLayers",
                "endTime": 79.619,
                "layerTreeId": 1
            },
            {
                "activityId": "Painting_15",
                "startTime": 82.518,
                "name": "Paint",
                "endTime": 82.594
            },
            {
                "activityId": "Painting_16",
                "startTime": 82.655,
                "name": "CompositeLayers",
                "endTime": 82.755,
                "layerTreeId": 1
            },
            {
                "activityId": "Painting_17",
                "startTime": 95.325,
                "name": "CompositeLayers",
                "endTime": 95.449,
                "layerTreeId": 1
            },
            {
                "activityId": "Painting_18",
                "startTime": 112.161,
                "name": "CompositeLayers",
                "endTime": 112.29,
                "layerTreeId": 1
            },
            {
                "activityId": "Painting_19",
                "startTime": 179.616,
                "name": "CompositeLayers",
                "endTime": 179.748,
                "layerTreeId": 1
            },
            {
                "activityId": "Painting_20",
                "startTime": 195.353,
                "name": "CompositeLayers",
                "endTime": 195.482,
                "layerTreeId": 1
            },
            {
                "activityId": "Painting_21",
                "startTime": 195.544,
                "name": "Paint",
                "endTime": 195.633
            },
            {
                "activityId": "Painting_22",
                "startTime": 195.703,
                "name": "CompositeLayers",
                "endTime": 195.764,
                "layerTreeId": 1
            },
            {
                "activityId": "Painting_23",
                "startTime": 212.136,
                "name": "CompositeLayers",
                "endTime": 212.314,
                "layerTreeId": 1
            },
            {
                "activityId": "Painting_24",
                "startTime": 228.857,
                "name": "CompositeLayers",
                "endTime": 229.024,
                "layerTreeId": 1
            },
            {
                "activityId": "Painting_25",
                "startTime": 232.666,
                "name": "CompositeLayers",
                "endTime": 232.683,
                "layerTreeId": 1
            }
        ]
    },
    {
        "id": "Deps",
        "objs": [
            {
                "time": 18.196,
                "a1": "Networking_0",
                "a2": "Loading_0"
            },
            {
                "time": 19.043,
                "a1": "Networking_0",
                "a2": "Scripting_0"
            },
            {
                "time": -1,
                "a1": "Loading_0",
                "a2": "Networking_1"
            },
            {
                "time": 30.024,
                "a1": "Networking_0",
                "a2": "Loading_1"
            },
            {
                "time": -1,
                "a1": "Scripting_0",
                "a2": "Loading_1"
            },
            {
                "time": -1,
                "a1": "Loading_0",
                "a2": "Loading_1"
            },
            {
                "time": 33.532,
                "a1": "Networking_0",
                "a2": "Scripting_1"
            },
            {
                "time": -1,
                "a1": "Networking_0",
                "a2": "Loading_2"
            },
            {
                "time": -1,
                "a1": "Scripting_1",
                "a2": "Loading_2"
            },
            {
                "time": -1,
                "a1": "Loading_1",
                "a2": "Loading_2"
            },
            {
                "time": -1,
                "a1": "Networking_0",
                "a2": "Scripting_2"
            },
            {
                "time": -1,
                "a1": "Networking_0",
                "a2": "Loading_3"
            },
            {
                "time": -1,
                "a1": "Scripting_2",
                "a2": "Loading_3"
            },
            {
                "time": -1,
                "a1": "Loading_2",
                "a2": "Loading_3"
            },
            {
                "time": -1,
                "a1": "Networking_0",
                "a2": "Scripting_3"
            },
            {
                "time": -1,
                "a1": "Networking_0",
                "a2": "Scripting_4"
            },
            {
                "time": -1,
                "a1": "Networking_0",
                "a2": "Scripting_5"
            },
            {
                "time": -1,
                "a1": "Networking_0",
                "a2": "Scripting_6"
            },
            {
                "time": -1,
                "a1": "Scripting_5",
                "a2": "Networking_2"
            },
            {
                "time": -1,
                "a1": "Scripting_5",
                "a2": "Networking_3"
            },
            {
                "time": 71.104,
                "a1": "Loading_3",
                "a2": "Networking_4"
            },
            {
                "time": -1,
                "a1": "Scripting_6",
                "a2": "Networking_5"
            },
            {
                "time": -1,
                "a1": "Networking_5",
                "a2": "Scripting_7"
            },
            {
                "time": -1,
                "a1": "Scripting_7",
                "a2": "Networking_6"
            },
            {
                "time": -1,
                "a1": "Networking_6",
                "a2": "Scripting_8"
            }
        ]
    },
    {
        "criticalPath": [
            "Networking_0",
            "Scripting_6",
            "Networking_5",
            "Scripting_7",
            "Networking_6",
            "Scripting_8"
        ],
        "networkingTime": 59.17,
        "computationTime": 124.63
    }
]